configparserplus/__init__.py
configparserplus/configparserplus.py
src/__init__.py
src/configparser_plus.py
configparser_plus-0.0.8.dist-info/LICENSE
configparser_plus-0.0.8.dist-info/METADATA
configparser_plus-0.0.8.dist-info/WHEEL
configparser_plus-0.0.8.dist-info/top_level.txt
configparser_plus-0.0.8.dist-info/RECORD
