Metadata-Version: 2.1
Name: configparser_plus
Version: 0.0.8
Summary: The advance version of origin configparser.
Home-page: https://gitee.com/leviathan-litan/python_config_file_plus
Author: Leviathan-litan
Author-email: leviathan_litan@163.com
License: UNKNOWN
Platform: UNKNOWN
Classifier: Programming Language :: Python :: 3
Classifier: Programming Language :: Python :: 2
Classifier: Development Status :: 5 - Production/Stable
